pimpmypillow-0.1.2.dist-info/DESCRIPTION.rst
pimpmypillow-0.1.2.dist-info/METADATA
pimpmypillow-0.1.2.dist-info/RECORD
pimpmypillow-0.1.2.dist-info/WHEEL
pimpmypillow-0.1.2.dist-info/entry_points.txt
pimpmypillow-0.1.2.dist-info/metadata.json
pimpmypillow-0.1.2.dist-info/top_level.txt
pmp/__init__.py
pmp/__main__.py
pmp/scripts/install-openjpeg.sh
pmp/settings/__init__.py
pmp/settings/archlinux.yml
pmp/settings/debian.yml
pmp/settings/ubuntu.yml
