Metadata-Version: 2.0
Name: pimpmypillow
Version: 0.1.2
Summary: Pimp My Pillow will install a fully working Pillow distribution, no more 'decoder * is not supported' messages!
Home-page: https://github.com/edvm/pimp-my-pillow
Author: Emiliano Dalla Verde Marcozzi
Author-email: edvm@fedoraproject.org
License: BSD
Platform: UNKNOWN
Classifier: Development Status :: 5 - Production/Stable
Classifier: Intended Audience :: Developers
Classifier: License :: OSI Approved :: GNU General Public License v3 (GPLv3)
Classifier: Operating System :: Unix
Classifier: Operating System :: POSIX
Classifier: Programming Language :: Python
Classifier: Programming Language :: Python :: 2.7
Classifier: Programming Language :: Python :: 3
Classifier: Programming Language :: Python :: 3.4
Classifier: Programming Language :: Python :: Implementation :: CPython
Classifier: Programming Language :: Python :: Implementation :: PyPy
Classifier: Topic :: Utilities
Requires-Dist: PyYAML
